usort/__init__.py
usort/__main__.py
usort/api.py
usort/cli.py
usort/config.py
usort/py.typed
usort/sorting.py
usort/stdlibs.py
usort/translate.py
usort/types.py
usort/util.py
usort/version.py
usort/tests/__init__.py
usort/tests/__main__.py
usort/tests/cli.py
usort/tests/config.py
usort/tests/functional.py
usort/tests/sorting.py
usort/tests/stdlibs.py
usort/tests/translate.py
usort/tests/types.py
usort/tests/util.py
usort-1.1.2.dist-info/METADATA
usort-1.1.2.dist-info/WHEEL
usort-1.1.2.dist-info/entry_points.txt
usort-1.1.2.dist-info/licenses/LICENSE
usort-1.1.2.dist-info/RECORD
