Metadata-Version: 2.4
Name: usort
Version: 1.1.2
Summary: Safe, minimal import sorting
Project-URL: Changelog, https://usort.readthedocs.io/en/latest/changelog.html
Project-URL: Documentation, https://usort.readthedocs.io
Project-URL: Github, https://github.com/facebook/usort
Author: Meta
Author-email: Tim Hatch <thatch@fb.com>, Amethyst Reese <amethyst@fb.com>
License: MIT License
License-File: LICENSE
Keywords: imports,isort,usort
Classifier: Development Status :: 5 - Production/Stable
Classifier: Intended Audience :: Developers
Classifier: License :: OSI Approved :: MIT License
Classifier: Topic :: Software Development
Classifier: Topic :: Utilities
Classifier: Typing :: Typed
Requires-Python: >=3.10
Requires-Dist: attrs>=21.2.0
Requires-Dist: click>=7.0.0
Requires-Dist: libcst>=0.3.7
Requires-Dist: moreorless>=0.3.0
Requires-Dist: stdlibs>=2021.4.1
Requires-Dist: tomli; python_version < '3.11'
Requires-Dist: trailrunner<2.0,>=1.0
Provides-Extra: dev
Requires-Dist: black==25.9.0; extra == 'dev'
Requires-Dist: click==8.1.8; extra == 'dev'
Requires-Dist: coverage==7.11.0; extra == 'dev'
Requires-Dist: flake8==7.3.0; extra == 'dev'
Requires-Dist: hatch==1.15.1; extra == 'dev'
Requires-Dist: mypy==1.18.2; extra == 'dev'
Requires-Dist: pessimist==0.9.3; extra == 'dev'
Requires-Dist: ufmt==2.8.0; extra == 'dev'
Requires-Dist: volatile==2.1.0; extra == 'dev'
Provides-Extra: docs
Requires-Dist: sphinx-mdinclude==0.6.2; extra == 'docs'
Requires-Dist: sphinx==7.4.7; extra == 'docs'
